insta_new.py
storage.py
instacooc-0.1.5.dist-info/DESCRIPTION.rst
instacooc-0.1.5.dist-info/METADATA
instacooc-0.1.5.dist-info/RECORD
instacooc-0.1.5.dist-info/WHEEL
instacooc-0.1.5.dist-info/metadata.json
instacooc-0.1.5.dist-info/top_level.txt
